LICENSE
airflow_oracle_snowflake_plugin/__init__.py
airflow_oracle_snowflake_plugin/hooks/custom_snowflake_hook.py
airflow_oracle_snowflake_plugin/oracle_to_snowflake_operator.py
airflow_oracle_snowflake_plugin/utils/sql_utils.py
airflow_oracle_snowflake_plugin-0.1.2.dist-info/LICENSE
airflow_oracle_snowflake_plugin-0.1.2.dist-info/WHEEL
airflow_oracle_snowflake_plugin-0.1.2.dist-info/METADATA
airflow_oracle_snowflake_plugin-0.1.2.dist-info/RECORD
