Metadata-Version: 2.1
Name: airflow-oracle-snowflake-plugin
Version: 0.1.2
Summary: Packag for airflow operator which copies tables from oracle database to snowflake.
Author: Ali Bhayani
Author-email: ali@cloudshuttle.com.au
Requires-Python: >=3.8,<4.0
Classifier: License :: OSI Approved :: MIT License
Classifier: Operating System :: OS Independent
Classifier: Programming Language :: Python :: 3
Classifier: Programming Language :: Python :: 3.8
Classifier: Programming Language :: Python :: 3.9
Classifier: Programming Language :: Python :: 3.10
Classifier: Programming Language :: Python :: 3.11
Classifier: Programming Language :: Python :: 3
Requires-Dist: apache-airflow-providers-oracle (>=3.4.0,<4.0.0)
Requires-Dist: apache-airflow-providers-snowflake (>=3.3.0,<4.0.0)
Requires-Dist: oracledb (>=1.2.0,<2.0.0)
Project-URL: CloudShuttle, https://www.cloudshuttle.com.au/
